itaxotools_popart_networks-0.1.2.dist-info/RECORD
itaxotools_popart_networks-0.1.2.dist-info/WHEEL
itaxotools_popart_networks-0.1.2.dist-info/entry_points.txt
itaxotools_popart_networks-0.1.2.dist-info/METADATA
itaxotools_popart_networks-0.1.2.dist-info/licenses/LICENSE.txt
itaxotools/_popart_networks.cpython-312-darwin.so
itaxotools/popart_networks/wrapper.py
itaxotools/popart_networks/__init__.py
itaxotools/popart_networks/types.py
itaxotools/popart_networks/preparse.py
itaxotools/_popart_networks/include/python_wrapper.h
itaxotools/_popart_networks/include/seqvertex.hpp
itaxotools/_popart_networks/include/popart_network.hpp
itaxotools/_popart_networks/include/seqgraph.hpp
itaxotools/_popart_networks/include/seqedge.hpp
itaxotools/_popart_networks/src/seqedge.cpp
itaxotools/_popart_networks/src/popart_network.cpp
itaxotools/_popart_networks/src/seqgraph.cpp
itaxotools/_popart_networks/src/seqvertex.cpp
itaxotools/_popart_networks/src/main.cpp
itaxotools/_popart_networks/src/python_wrapper.cpp
